MnaXGUI/__init__.py
mnaxgui-0.1.7.dist-info/licenses/LICENSE.txt
mnaxgui-0.1.7.dist-info/METADATA
mnaxgui-0.1.7.dist-info/WHEEL
mnaxgui-0.1.7.dist-info/top_level.txt
mnaxgui-0.1.7.dist-info/RECORD
