Metadata-Version: 2.4
Name: MnaXGUI
Version: 0.1.7
Summary: GUI package to make it easy
Author: MnaX
Requires-Python: >=3.10
License-File: LICENSE.txt
Dynamic: author
Dynamic: description
Dynamic: description-content-type
Dynamic: license-file
Dynamic: requires-python
Dynamic: summary
